DecAn/__init__.py
DecAn/decan.py
DecAn_karjakak-0.2.5.dist-info/METADATA
DecAn_karjakak-0.2.5.dist-info/WHEEL
DecAn_karjakak-0.2.5.dist-info/entry_points.txt
DecAn_karjakak-0.2.5.dist-info/top_level.txt
DecAn_karjakak-0.2.5.dist-info/RECORD
