Metadata-Version: 2.1
Name: DecAn-karjakak
Version: 0.2.5
Summary: DecAn is a tool for Analyze and Deconstruct chars in text for its position.
Home-page: https://github.com/kakkarja/DecAn
Author: karjakak
Author-email: kakkarja.github@gmail.com
License: BSD3 License
Platform: UNKNOWN
Classifier: Environment :: Console
Classifier: Environment :: Win32 (MS Windows)
Classifier: Intended Audience :: Developers
Classifier: Programming Language :: Python :: 3
Classifier: License :: OSI Approved :: BSD License
Requires-Python: >=3.9
Requires-Dist: GenPy-karjakak
